wantedposter/__init__.py
wantedposter/wantedposter.py
wantedposter/__pycache__/__init__.cpython-310.pyc
wantedposter/__pycache__/__init__.cpython-311.pyc
wantedposter/__pycache__/wantedposter.cpython-310.pyc
wantedposter/__pycache__/wantedposter.cpython-311.pyc
wantedposter/assets/fonts/Lilly__.ttf
wantedposter/assets/fonts/PlayfairDisplay-Bold.ttf
wantedposter/assets/image_components/dead_or_alive.jpg
wantedposter/assets/image_components/effect_frost.png
wantedposter/assets/image_components/effect_lightning.png
wantedposter/assets/image_components/no_portrait.jpg
wantedposter/assets/image_components/only_alive.jpg
wantedposter/assets/image_components/only_dead.jpg
wantedposter/assets/image_components/stamp_do_not_engage.png
wantedposter/assets/image_components/stamp_flee_on_sight.png
wantedposter/assets/image_components/stamp_warlord.png
wantedposter/assets/image_components/template.png
wantedposter/assets/image_components/texture_belly.jpg
wantedposter/assets/image_components/texture_name.jpg
wantedposter/assets/image_components/texture_portrait.jpg
one_piece_wanted_poster-0.0.13.dist-info/LICENSE
one_piece_wanted_poster-0.0.13.dist-info/METADATA
one_piece_wanted_poster-0.0.13.dist-info/WHEEL
one_piece_wanted_poster-0.0.13.dist-info/top_level.txt
one_piece_wanted_poster-0.0.13.dist-info/RECORD
