Metadata-Version: 2.1
Name: one-piece-wanted-poster
Version: 0.0.13
Summary: Python package to generate One Piece Wanted Posters
Home-page: https://github.com/Nickelza/one-piece-wanted-poster
Author: Nickelza
Author-email: nickjones7490@gmail.com
Project-URL: Bug Tracker, https://github.com/Nickelza/one-piece-wanted-poster/issues
Project-URL: repository, https://github.com/Nickelza/one-piece-wanted-poster
Classifier: Programming Language :: Python :: 3
Classifier: License :: OSI Approved :: MIT License
Classifier: Operating System :: OS Independent
Requires-Python: >=3.10
License-File: LICENSE
Requires-Dist: pillow ~=10.4.0
Requires-Dist: unidecode >=1.3.6
